alliancepy/__init__.py
alliancepy/cache.py
alliancepy/client.py
alliancepy/event.py
alliancepy/http.py
alliancepy/match.py
alliancepy/match_type.py
alliancepy/season.py
alliancepy/team.py
alliancepy/ext/aio/__init__.py
alliancepy/ext/aio/async_client.py
alliancepy/ext/aio/async_event.py
alliancepy/ext/aio/async_executor.py
alliancepy/ext/aio/async_http.py
alliancepy/ext/aio/async_match.py
alliancepy/ext/aio/async_team.py
alliancepy-1.5.2.dist-info/LICENSE
alliancepy-1.5.2.dist-info/METADATA
alliancepy-1.5.2.dist-info/WHEEL
alliancepy-1.5.2.dist-info/top_level.txt
alliancepy-1.5.2.dist-info/RECORD
