Metadata-Version: 2.1
Name: alliancepy
Version: 1.5.2
Summary: A library to access The Orange Alliance API
Home-page: https://github.com/karx1/alliancepy
Author: karx
Author-email: nerdstep710@gmail.com
License: MIT
Platform: UNKNOWN
Classifier: License :: OSI Approved :: MIT License
Classifier: Intended Audience :: Developers
Classifier: Natural Language :: English
Classifier: Operating System :: OS Independent
Requires-Python: >=3.6
Requires-Dist: requests
Provides-Extra: async
Requires-Dist: aiohttp[speedups] ; extra == 'async'
Requires-Dist: nest-asyncio ; extra == 'async'
Provides-Extra: docs
Requires-Dist: sphinx ; extra == 'docs'
Requires-Dist: sphinx-rtd-theme ; extra == 'docs'
